qmatsuite/__init__.py
qmatsuite-0.0.1.dist-info/METADATA
qmatsuite-0.0.1.dist-info/WHEEL
qmatsuite-0.0.1.dist-info/top_level.txt
qmatsuite-0.0.1.dist-info/RECORD
