Metadata-Version: 2.4
Name: qmatsuite
Version: 0.0.1
Summary: Placeholder package for QMatSuite — Quantum Materials Simulation & Integrative Environment.
Author: QMatSuite Developers
Requires-Python: >=3.8
